tiktoken_chatml/__init__.py
tiktoken_chatml-0.1.0.dist-info/METADATA
tiktoken_chatml-0.1.0.dist-info/WHEEL
tiktoken_chatml-0.1.0.dist-info/RECORD
