Metadata-Version: 2.1
Name: tiktoken-chatml
Version: 0.1.0
Summary: 
License: MIT
Author: melisa-writer
Author-email: melisa@writer.com
Requires-Python: >=3.10,<4.0
Classifier: License :: OSI Approved :: MIT License
Classifier: Programming Language :: Python :: 3
Classifier: Programming Language :: Python :: 3.10
Classifier: Programming Language :: Python :: 3.11
Classifier: Programming Language :: Python :: 3.12
Requires-Dist: tiktoken (>=0.7.0,<0.8.0)
